pyventus/__init__.py
pyventus/core/__init__.py
pyventus/core/collections/__init__.py
pyventus/core/collections/multi_bidict.py
pyventus/core/constants/__init__.py
pyventus/core/constants/stdout_colors.py
pyventus/core/exceptions/__init__.py
pyventus/core/exceptions/pyventus_exception.py
pyventus/core/exceptions/pyventus_import_exception.py
pyventus/core/loggers/__init__.py
pyventus/core/loggers/logger.py
pyventus/core/loggers/stdout_logger.py
pyventus/core/processing/__init__.py
pyventus/core/processing/processing_service.py
pyventus/core/processing/asyncio/__init__.py
pyventus/core/processing/asyncio/asyncio_processing_service.py
pyventus/core/processing/celery/__init__.py
pyventus/core/processing/celery/celery_processing_service.py
pyventus/core/processing/executor/__init__.py
pyventus/core/processing/executor/executor_processing_service.py
pyventus/core/processing/fastapi/__init__.py
pyventus/core/processing/fastapi/fastapi_processing_service.py
pyventus/core/processing/redis/__init__.py
pyventus/core/processing/redis/redis_processing_service.py
pyventus/core/subscriptions/__init__.py
pyventus/core/subscriptions/subscription.py
pyventus/core/subscriptions/subscription_context.py
pyventus/core/subscriptions/unsubscribable.py
pyventus/core/utils/__init__.py
pyventus/core/utils/callable_utils.py
pyventus/core/utils/repr_utils.py
pyventus/events/__init__.py
pyventus/events/emitters/__init__.py
pyventus/events/emitters/event_emitter.py
pyventus/events/emitters/event_emitter_utils.py
pyventus/events/handlers/__init__.py
pyventus/events/handlers/event_handler.py
pyventus/events/linkers/__init__.py
pyventus/events/linkers/event_linker.py
pyventus/events/subscribers/__init__.py
pyventus/events/subscribers/event_subscriber.py
pyventus/reactive/__init__.py
pyventus/reactive/observables/__init__.py
pyventus/reactive/observables/observable.py
pyventus/reactive/observables/observable_task.py
pyventus/reactive/observables/observable_utils.py
pyventus-0.7.2.dist-info/METADATA
pyventus-0.7.2.dist-info/WHEEL
pyventus-0.7.2.dist-info/licenses/LICENSE
pyventus-0.7.2.dist-info/RECORD
