Metadata-Version: 2.4
Name: pyventus
Version: 0.7.2
Summary: A powerful Python library for event-driven and reactive programming.
Project-URL: Homepage, https://github.com/mdapena/pyventus
Project-URL: Documentation, https://mdapena.github.io/pyventus
Project-URL: Repository, https://github.com/mdapena/pyventus
Author-email: Manuel Da Pena <dapensoft@gmail.com>
License-Expression: MIT
License-File: LICENSE
Keywords: EventEmitter,asynchronous,asynchronous programming,asynchronous-programming,event,event driven,event driven programming,event emitter,event emitters,event-driven,event-driven programming,events,observable,observables,observer,observer pattern,observers,reactive,reactive programming,reactive-programming
Classifier: Intended Audience :: Developers
Classifier: License :: OSI Approved :: MIT License
Classifier: Operating System :: OS Independent
Classifier: Programming Language :: Python
Classifier: Programming Language :: Python :: 3
Classifier: Programming Language :: Python :: 3 :: Only
Classifier: Programming Language :: Python :: 3.10
Classifier: Programming Language :: Python :: 3.11
Classifier: Programming Language :: Python :: 3.12
Classifier: Programming Language :: Python :: 3.13
Classifier: Programming Language :: Python :: 3.14
Classifier: Topic :: Software Development
Classifier: Topic :: Software Development :: Libraries
Classifier: Topic :: Software Development :: Libraries :: Python Modules
Classifier: Typing :: Typed
Requires-Python: >=3.10
Requires-Dist: typing-extensions>=4.8.0
Provides-Extra: all
Requires-Dist: celery>=5.3.5; extra == 'all'
Requires-Dist: fastapi>=0.95.2; extra == 'all'
Requires-Dist: rq>=1.15.0; extra == 'all'
Provides-Extra: celery
Requires-Dist: celery>=5.3.5; extra == 'celery'
Provides-Extra: dev
Requires-Dist: celery>=5.3.5; extra == 'dev'
Requires-Dist: coverage[toml]>=7.6.1; extra == 'dev'
Requires-Dist: fakeredis>=2.25.0; extra == 'dev'
Requires-Dist: fastapi>=0.95.2; extra == 'dev'
Requires-Dist: hatch>=1.12.0; extra == 'dev'
Requires-Dist: httpx>=0.23.0; extra == 'dev'
Requires-Dist: mike>=2.1.3; extra == 'dev'
Requires-Dist: mkdocs-git-committers-plugin-2>=2.3.0; extra == 'dev'
Requires-Dist: mkdocs-git-revision-date-localized-plugin>=1.2.9; extra == 'dev'
Requires-Dist: mkdocs-material>=9.5.37; extra == 'dev'
Requires-Dist: mkdocs-material[imaging]; extra == 'dev'
Requires-Dist: mkdocstrings[python]>=0.26.1; extra == 'dev'
Requires-Dist: mypy>=1.11.0; extra == 'dev'
Requires-Dist: pytest-asyncio>=0.24.0; extra == 'dev'
Requires-Dist: pytest>=8.0.0; extra == 'dev'
Requires-Dist: rq>=1.15.0; extra == 'dev'
Requires-Dist: ruff>=0.6.8; extra == 'dev'
Requires-Dist: tqdm>=4.66.5; extra == 'dev'
Provides-Extra: docs
Requires-Dist: mike>=2.1.3; extra == 'docs'
Requires-Dist: mkdocs-git-committers-plugin-2>=2.3.0; extra == 'docs'
Requires-Dist: mkdocs-git-revision-date-localized-plugin>=1.2.9; extra == 'docs'
Requires-Dist: mkdocs-material>=9.5.37; extra == 'docs'
Requires-Dist: mkdocs-material[imaging]; extra == 'docs'
Requires-Dist: mkdocstrings[python]>=0.26.1; extra == 'docs'
Provides-Extra: fastapi
Requires-Dist: fastapi>=0.95.2; extra == 'fastapi'
Provides-Extra: rq
Requires-Dist: rq>=1.15.0; extra == 'rq'
Provides-Extra: tests
Requires-Dist: celery>=5.3.5; extra == 'tests'
Requires-Dist: coverage[toml]>=7.6.1; extra == 'tests'
Requires-Dist: fakeredis>=2.25.0; extra == 'tests'
Requires-Dist: fastapi>=0.95.2; extra == 'tests'
Requires-Dist: httpx>=0.23.0; extra == 'tests'
Requires-Dist: mypy>=1.11.0; extra == 'tests'
Requires-Dist: pytest-asyncio>=0.24.0; extra == 'tests'
Requires-Dist: pytest>=8.0.0; extra == 'tests'
Requires-Dist: rq>=1.15.0; extra == 'tests'
Requires-Dist: ruff>=0.6.8; extra == 'tests'
Requires-Dist: tqdm>=4.66.5; extra == 'tests'
